relations_sqlite/__init__.py
relations_sqlite/clause.py
relations_sqlite/column.py
relations_sqlite/criteria.py
relations_sqlite/criterion.py
relations_sqlite/ddl.py
relations_sqlite/expression.py
relations_sqlite/index.py
relations_sqlite/query.py
relations_sqlite/sql.py
relations_sqlite/table.py
relations_sqlite-0.6.2.dist-info/LICENSE.txt
relations_sqlite-0.6.2.dist-info/METADATA
relations_sqlite-0.6.2.dist-info/WHEEL
relations_sqlite-0.6.2.dist-info/top_level.txt
relations_sqlite-0.6.2.dist-info/RECORD
